fanfair/__init__.py
fanfair/fanfair.py
FanFAIR-1.0.2.dist-info/LICENSE
FanFAIR-1.0.2.dist-info/METADATA
FanFAIR-1.0.2.dist-info/WHEEL
FanFAIR-1.0.2.dist-info/top_level.txt
FanFAIR-1.0.2.dist-info/RECORD
